Workbook

Sheet Fixed Assets
B1: Actual | H1: Forecast
A2: Line Item | B2: FY2020 | C2: FY2021 | D2: FY2022 | E2: FY2023 | F2: FY2024 | H2: FY2025 | I2: FY2026 | J2: FY2027 | K2: FY2028 | L2: FY2029
A3: Beginnig PP&E | B3: ='BS_ Historical'!B9 -> 10777 | C3: ='BS_ Historical'!C9 -> 9920 | D3: ='BS_ Historical'!D9 -> 9841 | E3: ='BS_ Historical'!E9 -> 9236 | F3: ='BS_ Historical'!F9 -> 10303 | H3: =F6 -> 11278 | I3: =H6 -> 12465.012 | J3: =I6 -> 13635.178 | K3: =J6 -> 14817.566 | L3: =K6 -> 15906.433
A4: D&A | B4: =IS_Historical!B15 -> 1536 | C4: =IS_Historical!C15 -> 1452 | D4: =IS_Historical!D15 -> 1260 | E4: =IS_Historical!E15 -> 1128 | F4: =IS_Historical!F15 -> 1075 | H4: =H11*IS_Historical!H3 -> 1012.988 | I4: =I11*IS_Historical!I3 -> 989.83401 | J4: =J11*IS_Historical!J3 -> 967.61224 | K4: =K11*IS_Historical!K3 -> 1051.1325 | L4: =L11*IS_Historical!L3 -> 1142.3182
A5: CapEx | B5: =B6+B4-B3 -> 679 | C5: =C6+C4-C3 -> 1373 | D5: =D6+D4-D3 -> 655 | E5: =E6+E4-E3 -> 2195 | F5: 2050 | H5: 2200 | I5: 2160 | J5: 2150 | K5: 2140 | L5: 2130
A6: Ending PP&E | B6: =C3 -> 9920 | C6: =D3 -> 9841 | D6: =E3 -> 9236 | E6: =F3 -> 10303 | F6: =F3-F4+F5 -> 11278 | H6: =H3-H4+H5 -> 12465.012 | I6: =I3-I4+I5 -> 13635.178 | J6: =J3-J4+J5 -> 14817.566 | K6: =K3-K4+K5 -> 15906.433 | L6: =L3-L4+L5 -> 16894.115
A10: Line Item | B10: FY2020 | C10: FY2021 | D10: FY2022 | E10: FY2023 | F10: FY2024 | H10: FY2025 | I10: FY2026 | J10: FY2027 | K10: FY2028 | L10: FY2029
A11: D&A as % of Revenue | B11: =B4/IS_Historical!B3 -> 0.046525716 | C11: =C4/IS_Historical!C3 -> 0.037563058 | D11: =D4/IS_Historical!D3 -> 0.0292996 | E11: =E4/IS_Historical!E3 -> 0.024653582 | F11: =F4/IS_Historical!F3 -> 0.022842694 | H11: 0.021 | I11: 0.02 | J11: 0.019 | K11: 0.02 | L11: 0.021
A12: CapEx as % of Revenue | B12: =B5/IS_Historical!B3 -> 0.020567032 | C12: =C5/IS_Historical!C3 -> 0.035519338 | D12: =D5/IS_Historical!D3 -> 0.015231141 | E12: =E5/IS_Historical!E3 -> 0.047973948 | F12: =F5/IS_Historical!F3 -> 0.043560485 | H12: =H5/IS_Historical!H3 -> 0.045607647 | I12: =I5/IS_Historical!I3 -> 0.043643681 | J12: =J5/IS_Historical!J3 -> 0.042217325 | K12: =K5/IS_Historical!K3 -> 0.040717989 | L12: =L5/IS_Historical!L3 -> 0.039157216

Sheet Free Cash FLow
B1: Actual | H1: Forecast
A2: Line Item | B2: FY2020 | C2: FY2021 | D2: FY2022 | E2: FY2023 | F2: FY2024 | H2: FY2025 | I2: FY2026 | J2: FY2027 | K2: FY2028 | L2: FY2029
A3: EBITDA | B3: =IS_Historical!B14 -> 10533 | C3: =IS_Historical!C14 -> 11760 | D3: =IS_Historical!D14 -> 12169 | E3: =IS_Historical!E14 -> 12439 | F3: =IS_Historical!F14 -> 11067 | H3: =IS_Historical!H14 -> 8730.992 | I3: =IS_Historical!I14 -> 14352.593 | J3: =IS_Historical!J14 -> 14819.745 | K3: =IS_Historical!K14 -> 15793.265 | L3: =IS_Historical!L14 -> 16346.029
A4: Depreciation and Amortization | B4: =IS_Historical!B15 -> 1536 | C4: =IS_Historical!C15 -> 1452 | D4: =IS_Historical!D15 -> 1260 | E4: =IS_Historical!E15 -> 1128 | F4: =IS_Historical!F15 -> 1075 | H4: =IS_Historical!H15 -> 1012.988 | I4: =IS_Historical!I15 -> 989.83401 | J4: =IS_Historical!J15 -> 967.61224 | K4: =IS_Historical!K15 -> 1051.1325 | L4: =IS_Historical!L15 -> 1142.3182
A5: Opearating Profit (EBIT) | B5: =B3-B4 -> 8997 | C5: =C3-C4 -> 10308 | D5: =D3-D4 -> 10909 | E5: =E3-E4 -> 11311 | F5: =F3-F4 -> 9992 | H5: =H3-H4 -> 7718.004 | I5: =I3-I4 -> 13362.759 | J5: =J3-J4 -> 13852.133 | K5: =K3-K4 -> 14742.133 | L5: =L3-L4 -> 15203.711
A6: Operating Taxes | B6: =B17*B5 -> 1828.1934 | C6: =C17*C5 -> 2174.428 | D6: =D17*D5 -> 1974.374 | E6: =E17*E5 -> 1964.0549 | F6: =F17*F5 -> 1860.8057 | H6: =H17*H5 -> 1620.7808 | I6: =I17*I5 -> 2552.287 | J6: =J17*J5 -> 2645.7574 | K6: =K17*K5 -> 2815.7473 | L6: =L17*L5 -> 2903.9088
A7: Net Operating Income After Taxes (NOPAT) | B7: =B5-B6 -> 7168.8066 | C7: =C5-C6 -> 8133.572 | D7: =D5-D6 -> 8934.626 | E7: =E5-E6 -> 9346.9451 | F7: =F5-F6 -> 8131.1943 | H7: =H5-H6 -> 6097.2232 | I7: =I5-I6 -> 10810.472 | J7: =J5-J6 -> 11206.376 | K7: =K5-K6 -> 11926.385 | L7: =L5-L6 -> 12299.802
A8: (+) Depreciation and Amortization | B8: ='Fixed Assets'!B4 -> 1536 | C8: ='Fixed Assets'!C4 -> 1452 | D8: ='Fixed Assets'!D4 -> 1260 | E8: ='Fixed Assets'!E4 -> 1128 | F8: ='Fixed Assets'!F4 -> 1075 | H8: ='Fixed Assets'!H4 -> 1012.988 | I8: ='Fixed Assets'!I4 -> 989.83401 | J8: ='Fixed Assets'!J4 -> 967.61224 | K8: ='Fixed Assets'!K4 -> 1051.1325 | L8: ='Fixed Assets'!L4 -> 1142.3182
A9: (-) Capital Expenditure | B9: ='Fixed Assets'!B5 -> 679 | C9: ='Fixed Assets'!C5 -> 1373 | D9: ='Fixed Assets'!D5 -> 655 | E9: ='Fixed Assets'!E5 -> 2195 | F9: ='Fixed Assets'!F5 -> 2050 | H9: ='Fixed Assets'!H5 -> 2200 | I9: ='Fixed Assets'!I5 -> 2160 | J9: ='Fixed Assets'!J5 -> 2150 | K9: ='Fixed Assets'!K5 -> 2140 | L9: ='Fixed Assets'!L5 -> 2130
A10: (-) Change in NWC | C10: =C11-B11 -> -1778 | D10: =D11-C11 -> -607 | E10: =E11-D11 -> 2007 | F10: =F11-E11 -> -7691 | H10: =-250 -> -250 | I10: =I11-H11 -> -219.5234 | J10: =J11-I11 -> -223.1391 | K10: =K11-J11 -> -315.41852 | L10: =L11-K11 -> -313.69227
A11: NWC | B11: =B12-B13 -> -3607 | C11: =C12-C13 -> -5385 | D11: =D12-D13 -> -5992 | E11: =E12-E13 -> -3985 | F11: =F12-F13 -> -11676 | H11: =H12-H13 -> -5247.1996 | I11: =I12-I13 -> -5466.723 | J11: =J12-J13 -> -5689.8621 | K11: =K12-K13 -> -6005.2806 | L11: =L12-L13 -> -6318.9729
A12: Current Assets | B12: ='Net Working Capital'!B7 -> 8326 | C12: ='Net Working Capital'!C7 -> 9920 | D12: ='Net Working Capital'!D7 -> 10960 | E12: ='Net Working Capital'!E7 -> 13069 | F12: ='Net Working Capital'!F7 -> 11426 | H12: ='Net Working Capital'!H7 -> 12255.385 | I12: ='Net Working Capital'!I7 -> 12577.358 | J12: ='Net Working Capital'!J7 -> 12966.434 | K12: ='Net Working Capital'!K7 -> 13431.58 | L12: ='Net Working Capital'!L7 -> 13940.669
A13: Curent Liabilities | B13: ='Net Working Capital'!B11 -> 11933 | C13: ='Net Working Capital'!C11 -> 15305 | D13: ='Net Working Capital'!D11 -> 16952 | E13: ='Net Working Capital'!E11 -> 17054 | F13: ='Net Working Capital'!F11 -> 23102 | H13: ='Net Working Capital'!H11 -> 17502.585 | I13: ='Net Working Capital'!I11 -> 18044.081 | J13: ='Net Working Capital'!J11 -> 18656.296 | K13: ='Net Working Capital'!K11 -> 19436.861 | L13: ='Net Working Capital'!L11 -> 20259.642
A14: Unlevered Free Cash Flow | C14: =C7+C8-C9-C10 -> 9990.572 | D14: =D7+D8-D9-D10 -> 10146.626 | E14: =E7+E8-E9-E10 -> 6272.9451 | F14: =F7+F8-F9-F10 -> 14847.194 | H14: =H7+H8-H9-H10 -> 5160.2112 | I14: =I7+I8-I9-I10 -> 9859.8296 | J14: =J7+J8-J9-J10 -> 10247.127 | K14: =K7+K8-K9-K10 -> 11152.936 | L14: =L7+L8-L9-L10 -> 11625.813
A17: Effective Tax Rate | B17: =IS_Historical!B12/IS_Historical!B11 -> 0.20320033 | C17: =IS_Historical!C12/IS_Historical!C11 -> 0.21094567 | D17: =IS_Historical!D12/IS_Historical!D11 -> 0.18098579 | E17: =IS_Historical!E12/IS_Historical!E11 -> 0.17364114 | F17: =IS_Historical!F12/IS_Historical!F11 -> 0.18622956 | H17: =IS_Historical!H12/IS_Historical!H11 -> 0.21 | I17: =IS_Historical!I12/IS_Historical!I11 -> 0.191 | J17: =IS_Historical!J12/IS_Historical!J11 -> 0.191 | K17: =IS_Historical!K12/IS_Historical!K11 -> 0.191 | L17: =IS_Historical!L12/IS_Historical!L11 -> 0.191
A19: Change in NWC as % of Revenue | C19: =C10/IS_Historical!B3 -> -0.05385594 | D19: =D10/IS_Historical!C3 -> -0.015703014 | E19: =E10/IS_Historical!D3 -> 0.046670077 | F19: =F10/IS_Historical!E3 -> -0.16809459 | H19: =H10/IS_Historical!H3 -> -0.0051826871 | I19: =I10/IS_Historical!I3 -> -0.0044355598 | J19: =J10/IS_Historical!J3 -> -0.0043815515 | K19: =K10/IS_Historical!K3 -> -0.006001499 | L19: =L10/IS_Historical!L3 -> -0.005766815
A22: Note : Free cash flow is driven by normalized ΔNWC assumptions to avoid distortion from one-off working capital swings

Sheet Net Working Capital
B1: Actual | H1: Forecast
A2: Line Item | B2: FY2020 | C2: FY2021 | D2: FY2022 | E2: FY2023 | F2: FY2024 | H2: FY2025 | I2: FY2026 | J2: FY2027 | K2: FY2028 | L2: FY2029
A4: Accounts Receivable | B4: ='BS_ Historical'!B4 -> 3144 | C4: ='BS_ Historical'!C4 -> 3512 | D4: ='BS_ Historical'!D4 -> 3487 | E4: ='BS_ Historical'!E4 -> 3410 | F4: ='BS_ Historical'!F4 -> 3569 | H4: =H17*IS_Historical!H3/360 -> 4028.2149 | I4: =I17*IS_Historical!I3/360 -> 4124.3084 | J4: =J17*IS_Historical!J3/360 -> 4243.9133 | K4: =K17*IS_Historical!K3/360 -> 4379.7186 | L4: =L17*IS_Historical!L3/360 -> 4533.0087
A5: Inventory | B5: ='BS_ Historical'!B5 -> 3266 | C5: ='BS_ Historical'!C5 -> 3414 | D5: ='BS_ Historical'!D5 -> 4233 | E5: ='BS_ Historical'!E5 -> 4424 | F5: ='BS_ Historical'!F5 -> 4728 | H5: =H18*IS_Historical!H4/360 -> 4447.8893 | I5: =I18*IS_Historical!I4/360 -> 4575.5077 | J5: =J18*IS_Historical!J4/360 -> 4732.5292 | K5: =K18*IS_Historical!K4/360 -> 4934.1909 | L5: =L18*IS_Historical!L4/360 -> 5145.8715
A6: Pre-Paid Expenses | B6: ='BS_ Historical'!B6 -> 1916 | C6: ='BS_ Historical'!C6 -> 2994 | D6: ='BS_ Historical'!D6 -> 3240 | E6: ='BS_ Historical'!E6 -> 5235 | F6: ='BS_ Historical'!F6 -> 3129 | H6: =H22*IS_Historical!H$3 -> 3779.281 | I6: =I22*IS_Historical!I$3 -> 3877.5423 | J6: =J22*IS_Historical!J$3 -> 3989.991 | K6: =K22*IS_Historical!K$3 -> 4117.6707 | L6: =L22*IS_Historical!L$3 -> 4261.7892
A7: Current Assets | B7: =SUM(B4:B6) -> 8326 | C7: =SUM(C4:C6) -> 9920 | D7: =SUM(D4:D6) -> 10960 | E7: =SUM(E4:E6) -> 13069 | F7: =SUM(F4:F6) -> 11426 | H7: =SUM(H4:H6) -> 12255.385 | I7: =SUM(I4:I6) -> 12577.358 | J7: =SUM(J4:J6) -> 12966.434 | K7: =SUM(K4:K6) -> 13431.58 | L7: =SUM(L4:L6) -> 13940.669
A9: Accounts Payable and Accrued Expenses | B9: 11145 | C9: 14619 | D9: 15749 | E9: 15485 | F9: 21715 | H9: =H19*IS_Historical!H4/360 -> 16216.051 | I9: =I19*IS_Historical!I4/360 -> 16724.098 | J9: =J19*IS_Historical!J4/360 -> 17298.033 | K9: =K19*IS_Historical!K4/360 -> 18035.134 | L9: =L19*IS_Historical!L4/360 -> 18808.855
A10: Accrued Income Taxes | B10: 788 | C10: 686 | D10: 1203 | E10: 1569 | F10: 1387 | H10: =H23*IS_Historical!H$3 -> 1286.5335 | I10: =I23*IS_Historical!I$3 -> 1319.9833 | J10: =J23*IS_Historical!J$3 -> 1358.2628 | K10: =K23*IS_Historical!K$3 -> 1401.7273 | L10: =L23*IS_Historical!L$3 -> 1450.7877
A11: Total Current Liabilities | B11: =SUM(B9,B10) -> 11933 | C11: =SUM(C9,C10) -> 15305 | D11: =SUM(D9,D10) -> 16952 | E11: =SUM(E9,E10) -> 17054 | F11: =SUM(F9,F10) -> 23102 | H11: =SUM(H9,H10) -> 17502.585 | I11: =SUM(I9,I10) -> 18044.081 | J11: =SUM(J9,J10) -> 18656.296 | K11: =SUM(K9,K10) -> 19436.861 | L11: =SUM(L9,L10) -> 20259.642
A16: Line Item | B16: FY2020 | C16: FY2021 | D16: FY2022 | E16: FY2023 | F16: FY2024 | H16: FY2025 | I16: FY2026 | J16: FY2027 | K16: FY2028 | L16: FY2029
A17: Days Sales Outstanding | B17: =(B4/IS_Historical!B3)*360 -> 34.283637 | C17: =(C4/IS_Historical!C3)*360 -> 32.7078 | D17: =(D4/IS_Historical!D3)*360 -> 29.190773 | E17: =(E4/IS_Historical!E3)*360 -> 26.830441 | F17: =(F4/IS_Historical!F3)*360 -> 27.301587 | H17: =AVERAGE(B17:F17) -> 30.062848 | I17: 30 | J17: 30 | K17: 30 | L17: 30
A18: Days Inventory Outstanding | B18: =(B5/IS_Historical!B4)*360 -> 87.52773 | C18: =(C5/IS_Historical!C4)*360 -> 80.031256 | D18: =(D5/IS_Historical!D4)*360 -> 84.66 | E18: =(E5/IS_Historical!E4)*360 -> 85.99568 | F18: =(F5/IS_Historical!F4)*360 -> 92.888016 | H18: =AVERAGE(B18:F18) -> 86.220536 | I18: 86 | J18: 86 | K18: 86 | L18: 86
A19: Days Payable Outstanding | B19: =(B9/IS_Historical!B4)*360 -> 298.68235 | C19: =(C9/IS_Historical!C4)*360 -> 342.69975 | D19: =(D9/IS_Historical!D4)*360 -> 314.98 | E19: =(E9/IS_Historical!E4)*360 -> 301.00432 | F19: =(F9/IS_Historical!F4)*360 -> 426.62083 | H19: =AVERAGE(B19:E19) -> 314.3416 | I19: =AVERAGE(B19:E19) -> 314.3416 | J19: =AVERAGE(B19:E19) -> 314.3416 | K19: =AVERAGE(B19:E19) -> 314.3416 | L19: =AVERAGE(B19:E19) -> 314.3416
A22: Pre-Paid Expenses as % of Revenue | B22: =B6/IS_Historical!B$3 -> 0.058035985 | C22: =C6/IS_Historical!C$3 -> 0.077454404 | D22: =D6/IS_Historical!D$3 -> 0.075341829 | E22: =E6/IS_Historical!E$3 -> 0.11441623 | F22: =F6/IS_Historical!F$3 -> 0.066488175 | H22: =AVERAGE(B22:F22) -> 0.078347324 | I22: =H22 -> 0.078347324 | J22: =I22 -> 0.078347324 | K22: =J22 -> 0.078347324 | L22: =K22 -> 0.078347324
A23: Accrued Income Taxes as % of Revenue | B23: =B10/IS_Historical!B$3 -> 0.023868662 | C23: =C10/IS_Historical!C$3 -> 0.017746734 | D23: =D10/IS_Historical!D$3 -> 0.027974142 | E23: =E10/IS_Historical!E$3 -> 0.034292084 | F23: =F10/IS_Historical!F$3 -> 0.029472387 | H23: =AVERAGE(B23:F23) -> 0.026670802 | I23: =H23 -> 0.026670802 | J23: =I23 -> 0.026670802 | K23: =J23 -> 0.026670802 | L23: =K23 -> 0.026670802

Sheet IS_Historical
B1: Actual | H1: Forecast
A2: Line item | B2: FY2020 | C2: FY2021 | D2: FY2022 | E2: FY2023 | F2: FY2024 | H2: FY2025 | I2: FY2026 | J2: FY2027 | K2: FY2028 | L2: FY2029
A3: Revenue | B3: 33014 | C3: 38655 | D3: 43004 | E3: 45754 | F3: 47061 | H3: =F3*(1+H21) -> 48237.525 | I3: =H3*(1+I21) -> 49491.701 | J3: =I3*(1+J21) -> 50926.96 | K3: =J3*(1+K21) -> 52556.623 | L3: =K3*(1+L21) -> 54396.104
A4: COGS | B4: 13433 | C4: 15357 | D4: 18000 | E4: 18520 | F4: 18324 | H4: =H3*H22 -> 18571.447 | I4: =I3*I22 -> 19153.288 | J4: =J3*J22 -> 19810.587 | K4: =K3*K22 -> 20654.753 | L4: =L3*L22 -> 21540.857
A5: Gross Profit | B5: 19581 | C5: 23298 | D5: 25004 | E5: 27234 | F5: 28737 | H5: =H3-H4 -> 29666.078 | I5: =I3-I4 -> 30338.412 | J5: =J3-J4 -> 31116.373 | K5: =K3-K4 -> 31901.87 | L5: =L3-L4 -> 32855.247
A6: SG&A Expense | B6: 9731 | C6: 12144 | D6: 12880 | E6: 13972 | F6: 14582 | H6: =H3*H23 -> 15194.82 | I6: =I3*I23 -> 15490.902 | J6: =J3*J23 -> 15787.358 | K6: =K3*K23 -> 15661.874 | L6: =L3*L23 -> 16046.851
A7: Other Operating Expenses | B7: -853 | C7: -846 | D7: -1215 | E7: -1951 | F7: -4163 | H7: =-H3*H24 -> -6753.2535 | I7: =-I3*I24 -> -1484.751 | J7: =-J3*J24 -> -1476.8818 | K7: =-K3*K24 -> -1497.8637 | L7: =-L3*L24 -> -1604.6851
A8: Operating Expenses | B8: 10584 | C8: 12990 | D8: 14095 | E8: 15923 | F8: 18745 | H8: =H6-H7 -> 21948.074 | I8: =I6-I7 -> 16975.653 | J8: =J6-J7 -> 17264.239 | K8: =K6-K7 -> 17159.737 | L8: =L6-L7 -> 17651.536
A9: Operating Income | B9: 8997 | C9: 10308 | D9: 10909 | E9: 11311 | F9: 9992 | H9: =H5-H8 -> 7718.004 | I9: =I5-I8 -> 13362.759 | J9: =J5-J8 -> 13852.133 | K9: =K5-K8 -> 14742.133 | L9: =L5-L8 -> 15203.711
A10: Total Non-Opearting Income/Expense | B10: 752 | C10: 2117 | D10: 777 | E10: 1641 | F10: 3094 | H10: =H3*H25 -> 2894.2515 | I10: =I3*I25 -> 1781.7012 | J10: =J3*J25 -> 1629.6627 | K10: =K3*K25 -> 1471.5854 | L10: =L3*L25 -> 1359.9026
A11: Pre-Tax Income | B11: 9749 | C11: 12425 | D11: 11686 | E11: 12952 | F11: 13086 | H11: =SUM(H9:H10) -> 10612.255 | I11: =SUM(I9:I10) -> 15144.46 | J11: =SUM(J9:J10) -> 15481.796 | K11: =SUM(K9:K10) -> 16213.718 | L11: =SUM(L9:L10) -> 16563.614
A12: Income Tax | B12: 1981 | C12: 2621 | D12: 2115 | E12: 2249 | F12: 2437 | H12: =H11*H26 -> 2228.5737 | I12: =I11*I26 -> 2892.5919 | J12: =J11*J26 -> 2957.023 | K12: =K11*K26 -> 3096.8202 | L12: =L11*L26 -> 3163.6502
A13: Net Income | B13: 7747 | C13: 9771 | D13: 9542 | E13: 10714 | F13: 10631 | H13: =H11-H12 -> 8383.6818 | I13: =I11-I12 -> 12251.868 | J13: =J11-J12 -> 12524.773 | K13: =K11-K12 -> 13116.898 | L13: =L11-L12 -> 13399.964
A14: EBITDA | B14: 10533 | C14: 11760 | D14: 12169 | E14: 12439 | F14: 11067 | H14: =H9+H15 -> 8730.992 | I14: =I9+I15 -> 14352.593 | J14: =J9+J15 -> 14819.745 | K14: =K9+K15 -> 15793.265 | L14: =L9+L15 -> 16346.029
A15: Depreciation & Amortization | B15: =B14-B16 -> 1536 | C15: =C14-C16 -> 1452 | D15: =D14-D16 -> 1260 | E15: =E14-E16 -> 1128 | F15: =F14-F16 -> 1075 | H15: ='Fixed Assets'!H4 -> 1012.988 | I15: ='Fixed Assets'!I4 -> 989.83401 | J15: ='Fixed Assets'!J4 -> 967.61224 | K15: ='Fixed Assets'!K4 -> 1051.1325 | L15: ='Fixed Assets'!L4 -> 1142.3182
A16: EBIT | B16: 8997 | C16: 10308 | D16: 10909 | E16: 11311 | F16: 9992 | H16: =H14-H15 -> 7718.004 | I16: =I14-I15 -> 13362.759 | J16: =J14-J15 -> 13852.133 | K16: =K14-K15 -> 14742.133 | L16: =L14-L15 -> 15203.711
B19: Actual | H19: Assumptions
A20: Fiscal year | B20: FY2020 | C20: FY2021 | D20: FY2022 | E20: FY2023 | F20: FY2024 | H20: FY2025 | I20: FY2026 | J20: FY2027 | K20: FY2028 | L20: FY2029
A21: Revenue Growth % | C21: =(C3-B3)/B3 -> 0.1708669 | D21: =(D3-C3)/C3 -> 0.11250808 | E21: =(E3-D3)/D3 -> 0.06394754 | F21: =(F3-E3)/E3 -> 0.028565808 | H21: 0.025 | I21: 0.026 | J21: 0.029 | K21: 0.032 | L21: 0.035
A22: COGS as % of Revenue | B22: =B4/B3 -> 0.40688799 | C22: =C4/C3 -> 0.39728366 | D22: =D4/D3 -> 0.41856571 | E22: =E4/E3 -> 0.40477335 | F22: =F4/F3 -> 0.38936699 | H22: 0.385 | I22: 0.387 | J22: 0.389 | K22: 0.393 | L22: 0.396
A23: SG&A as % of Revenue | B23: =B6/B3 -> 0.29475374 | C23: =C6/C3 -> 0.31416376 | D23: =D6/D3 -> 0.29950702 | E23: =E6/E3 -> 0.30537221 | F23: =F6/F3 -> 0.30985317 | H23: 0.315 | I23: 0.313 | J23: 0.31 | K23: 0.298 | L23: 0.295
A24: OOE as % of Revenue | B24: =-B7/B3 -> 0.025837523 | C24: =-C7/C3 -> 0.021885914 | D24: =-D7/D3 -> 0.028253186 | E24: =-E7/E3 -> 0.042641081 | F24: =-F7/F3 -> 0.088459659 | H24: 0.14 | I24: 0.03 | J24: 0.029 | K24: 0.0285 | L24: 0.0295
A25: Total Non-Operating Income as % of Revenue | B25: =B10/B3 -> 0.022778215 | C25: =C10/C3 -> 0.054766524 | D25: =D10/D3 -> 0.018068087 | E25: =E10/E3 -> 0.035865717 | F25: =F10/F3 -> 0.065744459 | H25: 0.06 | I25: 0.036 | J25: 0.032 | K25: 0.028 | L25: 0.025
A26: Income tax | B26: =B12/B11 -> 0.20320033 | C26: =C12/C11 -> 0.21094567 | D26: =D12/D11 -> 0.18098579 | E26: =E12/E11 -> 0.17364114 | F26: =F12/F11 -> 0.18622956 | H26: 0.21 | I26: 0.191 | J26: 0.191 | K26: 0.191 | L26: 0.191
A28: Gross Margin | B28: =B5/B3 -> 0.59311201 | C28: =C5/C3 -> 0.60271634 | D28: =D5/D3 -> 0.58143429 | E28: =E5/E3 -> 0.59522665 | F28: =F5/F3 -> 0.61063301 | H28: =H5/H3 -> 0.615 | I28: =I5/I3 -> 0.613 | J28: =J5/J3 -> 0.611 | K28: =K5/K3 -> 0.607 | L28: =L5/L3 -> 0.604
A29: EBIT Margin | B29: =B9/B3 -> 0.27252075 | C29: =C9/C3 -> 0.26666667 | D29: =D9/D3 -> 0.25367408 | E29: =E9/E3 -> 0.24721336 | F29: =F9/F3 -> 0.21232018 | H29: =H9/H3 -> 0.16 | I29: =I9/I3 -> 0.27 | J29: =J9/J3 -> 0.272 | K29: =K9/K3 -> 0.2805 | L29: =L9/L3 -> 0.2795
A30: Net Income Margin | B30: =B13/B3 -> 0.23465802 | C30: =C13/C3 -> 0.25277454 | D30: =D13/D3 -> 0.22188634 | E30: =E13/E3 -> 0.23416532 | F30: =F13/F3 -> 0.2258983 | H30: =H13/H3 -> 0.1738 | I30: =I13/I3 -> 0.247554 | J30: =J13/J3 -> 0.245936 | K30: =K13/K3 -> 0.2495765 | L30: =L13/L3 -> 0.2463405

Sheet BS_ Historical
B1: Actual
A2: Line Item | B2: FY2020 | C2: FY2021 | D2: FY2022 | E2: FY2023 | F2: FY2024
A3: Cash | B3: 10914 | C3: 12625 | D3: 11631 | E3: 13663 | F3: 14571
A4: Accounts Receivable | B4: 3144 | C4: 3512 | D4: 3487 | E4: 3410 | F4: 3569
A5: Inventory | B5: 3266 | C5: 3414 | D5: 4233 | E5: 4424 | F5: 4728
A6: Pre-Paid Expenses | B6: 1916 | C6: 2994 | D6: 3240 | E6: 5235 | F6: 3129
A7: Other Current Assets | B7: na | C7: na | D7: na | E7: na | F7: na
A8: Total Current Assets | B8: 19240 | C8: 22545 | D8: 22591 | E8: 26732 | F8: 25997
A9: PP&E | B9: 10777 | C9: 9920 | D9: 9841 | E9: 9236 | F9: 10303
A10: Long Term Investments | B10: 20085 | C10: 18416 | D10: 18765 | E10: 19671 | F10: 18087
A11: Intangibles / Other Assets | B11: 28550 | C11: 34613 | D11: 33631 | E11: 32707 | F11: 31440
A12: Other Long-Term Assets | B12: 6184 | C12: 6731 | D12: 6189 | E12: 7796 | F12: 13403
A13: Total Assets | B13: 87296 | C13: 94354 | D13: 92763 | E13: 97703 | F13: 100549
A14: Total Current Liabilities | B14: 14601 | C14: 19950 | D14: 19724 | E14: 23571 | F14: 25249
A15: Long-Term Debt | B15: 40125 | C15: 38116 | D15: 36377 | E15: 35547 | F15: 42375
A16: Other Liabilities | B16: 9453 | C16: 8607 | D16: 7922 | E16: 8466 | F16: 4084
A17: Total Long-Term Liabilities | B17: 51411 | C17: 49544 | D17: 47213 | E17: 46652 | F17: 48928
A18: Total Liabilities | B18: 66012 | C18: 69494 | D18: 66937 | E18: 70223 | F18: 74177
A19: Retained Earnings | B19: 66555 | C19: 69094 | D19: 71019 | E19: 73782 | F19: 76054
... A22: Total Liabilities and Share Holders Equity | B22: 87296 | C22: 94354 | D22: 92763 | E22: 97703 | F22: 100549
A27: Current Ratio | B27: =B8/B14 -> 1.317718 | C27: =C8/C14 -> 1.1300752 | D27: =D8/D14 -> 1.1453559 | E27: =E8/E14 -> 1.1341055 | F27: =F8/F14 -> 1.0296249
A28: Quick Ratio | B28: =(B3+B4)/B14 -> 0.96281077 | C28: =(C3+C4)/C14 -> 0.80887218 | D28: =(D3+D4)/D14 -> 0.76647739 | E28: =(E3+E4)/E14 -> 0.72432226 | F28: =(F3+F4)/F14 -> 0.71844429
A29: Cash Ratio | B29: =B3/B14 -> 0.74748305 | C29: =C3/C14 -> 0.63283208 | D29: =D3/D14 -> 0.58968769 | E29: =E3/E14 -> 0.57965296 | F29: =F3/F14 -> 0.57709216
A31: Debt to Equity Ratio | B31: =B18/B21 -> 3.1014847 | C31: =C18/C21 -> 2.7954143 | D31: =D18/D21 -> 2.5918454 | E31: =E18/E21 -> 2.5554221 | F31: =F18/F21 -> 2.812718
A33: ROE | B33: =IS_Historical!B13/'BS_ Historical'!B21 -> 0.36398233 | C33: =IS_Historical!C13/'BS_ Historical'!C21 -> 0.39304103 | D33: =IS_Historical!D13/'BS_ Historical'!D21 -> 0.36947262 | E33: =IS_Historical!E13/'BS_ Historical'!E21 -> 0.38988355 | F33: =IS_Historical!F13/'BS_ Historical'!F21 -> 0.40311694

Sheet CF_Historical
B1: Actual
A2: Line Item | B2: FY2020 | C2: FY2021 | D2: FY2022 | E2: FY2023 | F2: FY2024
A3: Net Income | B3: 7768 | C3: 9804 | D3: 9571 | E3: 10703 | F3: 10649
A4: Total Depreciation & Amortization | B4: 1536 | C4: 1452 | D4: 1260 | E4: 1128 | F4: 1075
A5: Other Non-Cash Items | B5: -150 | C5: 44 | D5: 792 | E5: 614 | F5: 1315
A6: Total Non-Cash Items | B6: 1386 | C6: 1496 | D6: 2052 | E6: 1742 | F6: 2390
A7: Change in Assets/Liabilities | B7: 690 | C7: 1325 | D7: -605 | E7: -846 | F7: -6234
A8: Total change in Assets/Liabilities | B8: 690 | C8: 1325 | D8: -605 | E8: -846 | F8: -6234
A9: Cash Flow from Operating Activities | B9: 9844 | C9: 12625 | D9: 11018 | E9: 11599 | F9: 6805
A10: Net Change in PP&E | B10: -988 | C10: -1259 | D10: -1409 | E10: -1778 | F10: -2024
A11: Net Acquisitions/Divestitures | B11: -863 | C11: -2586 | D11: 385 | E11: 368 | F11: 3170
A12: Net Change in Short-Term Investments | B12: 252 | C12: 1029 | D12: 1020 | E12: -2344 | F12: 949
A13: Other Investing Activities | B13: 122 | C13: 51 | D13: -759 | E13: 405 | F13: 429
A14: Cash Flow from Investing Activities | B14: -1477 | C14: -2765 | D14: -763 | E14: -3349 | F14: 2524
... A21: Net Cash Flow | B21: 58 | C21: 2574 | D21: -506 | E21: -495 | F21: 1136

Sheet DCF
B1: Actual | H1: Forecast
A2: Line Item | B2: FY2020 | C2: FY2021 | D2: FY2022 | E2: FY2023 | F2: FY2024 | H2: FY2025 | I2: FY2026 | J2: FY2027 | K2: FY2028 | L2: FY2029
A3: Unlevered Free Cash Flow | C3: ='Free Cash FLow'!C14 -> 9990.572 | D3: ='Free Cash FLow'!D14 -> 10146.626 | E3: ='Free Cash FLow'!E14 -> 6272.9451 | F3: ='Free Cash FLow'!F14 -> 14847.194 | H3: ='Free Cash FLow'!H14 -> 5160.2112 | I3: ='Free Cash FLow'!I14 -> 9859.8296 | J3: ='Free Cash FLow'!J14 -> 10247.127 | K3: ='Free Cash FLow'!K14 -> 11152.936 | L3: ='Free Cash FLow'!L14 -> 11625.813
A5: Projection Year | H5: 1 | I5: 2 | J5: 3 | K5: 4 | L5: 5
A6: Present Value of Free Cash Flow | H6: =H3/(1+$B$12)^H5 -> 4829.6266 | I6: =I3/(1+$B$12)^I5 -> 8636.9731 | J6: =J3/(1+$B$12)^J5 -> 8401.1813 | K6: =K3/(1+$B$12)^K5 -> 8558.0248 | L6: =L3/(1+$B$12)^L5 -> 8349.3703
A9: Implied Share Price Calculation
A10: Sum of PV of FCF | B10: =SUM(H6:L6) -> 38775.176
A11: Growth Rate | B11: 0.02
A12: WACC | B12: =WACC!C19 -> 0.068449304
A13: Terminal Value | B13: =(L3*(1+B11))/(B12-B11) -> 244757.47
A14: PV of Terminal Value | B14: =B13/(1+B12)^L5 -> 175778.74
A15: Entreprise Value | B15: =B14+B10 -> 214553.92
A16: (+) Cash | B16: ='BS_ Historical'!F3 -> 14571
A17: (-) Debt | B17: =WACC!C5 -> 48928
A18: (-) Minority Interest | B18: 1516
A19: Equity Value | B19: =B15+B16-B17-B18 -> 178680.92
A20: Diluted Shares Outstanding | B20: 4300
A21: Implied Share Price | B21: =B19/B20 -> 41.553702

Sheet WACC
A2: Weighted Average Cost of Capital (WACC)
A4: Equity | C4: 301000
A5: Debt | C5: ='BS_ Historical'!F17 -> 48928
A7: Cost of Debt | C7: =1656/C5 -> 0.033845651
A8: Tax Rate | C8: =AVERAGE(IS_Historical!B26:F26) -> 0.1910005
A9: D/(D+E) | C9: =C5/SUM(C4:C5) -> 0.13982305
A10: After Tax Cost of Debt | C10: =C7*(1-C8) -> 0.027381115
A12: Risk Free Rate (10-Yr Treasury Yield) | C12: 0.041
A13: Expected Market Return | C13: =C14+C12 -> 0.0935
A14: Equity Risk Premium | C14: =AVERAGE(4.5,6)% -> 0.0525
A15: Levered Beta | C15: =AVERAGE(0.6,0.7) -> 0.65
A16: E/(D+E) | C16: =C4/SUM(C4:C5) -> 0.86017695
A17: Cost of Equity | C17: =(C15*C14)+C12 -> 0.075125
A19: WACC | C19: =(C10*C9)+(C17*C16) -> 0.068449304

Sheet Sources
A1: Data source - Macrotrends
A2: Fiscal years - 2020 to 2024
